naive_feature_selection/__init__.py
naive_feature_selection/naive_feature_selection.py
naive_feature_selection-0.0.1.dist-info/LICENSE
naive_feature_selection-0.0.1.dist-info/METADATA
naive_feature_selection-0.0.1.dist-info/WHEEL
naive_feature_selection-0.0.1.dist-info/top_level.txt
naive_feature_selection-0.0.1.dist-info/RECORD
