Metadata-Version: 2.1
Name: naive-feature-selection
Version: 0.0.1
Summary: Naive Feature Selection
Home-page: https://github.com/aspremon/NaiveFeatureSelection
Author: Armin Askari, Alexandre d'Aspremont, Laurent El Ghaoui
Author-email: aspremon@ens.fr
License: UNKNOWN
Platform: UNKNOWN
Classifier: Programming Language :: Python :: 3
Classifier: License :: OSI Approved :: MIT License
Classifier: Operating System :: OS Independent
Requires-Python: >=3.5.0
Requires-Dist: scikit-learn
